xeuledoc/__init__.py
xeuledoc/core.py
xeuledoc-2.1.dist-info/LICENSE.md
xeuledoc-2.1.dist-info/METADATA
xeuledoc-2.1.dist-info/WHEEL
xeuledoc-2.1.dist-info/entry_points.txt
xeuledoc-2.1.dist-info/top_level.txt
xeuledoc-2.1.dist-info/RECORD
